scandal/__init__.py
scandal/_config.py
scandal/credentials/__init__.py
scandal/credentials/base.py
scandal/credentials/client.py
scandal/credentials/device.py
scandal/credentials/oauth.py
scandal/dbapi/__init__.py
scandal/dbapi/connection.py
scandal/dbapi/proxy.py
scandal/sqlalchemy/__init__.py
scandal/sqlalchemy/bigquery.py
scandal-0.1.9.dist-info/METADATA
scandal-0.1.9.dist-info/WHEEL
scandal-0.1.9.dist-info/entry_points.txt
scandal-0.1.9.dist-info/RECORD
