Metadata-Version: 2.1
Name: scandal
Version: 0.1.9
Summary: 
Author: Nicholas Gates
Author-email: nick@nickgates.com
Requires-Python: >=3.9,<4
Classifier: Programming Language :: Python :: 3
Classifier: Programming Language :: Python :: 3.9
Classifier: Programming Language :: Python :: 3.10
Classifier: Programming Language :: Python :: 3.11
Provides-Extra: sqlalchemy
Requires-Dist: PyJWT (>=2.6.0,<3.0.0)
Requires-Dist: adbc-driver-flightsql (>=0.4.0,<0.5.0)
Requires-Dist: keyring (>=23.13.1,<24.0.0)
Requires-Dist: pyarrow (>=12.0.0,<13.0.0)
Requires-Dist: requests (>=2.29.0,<3.0.0)
Requires-Dist: sqlalchemy (>=1.2.0,<2.0.0dev) ; extra == "sqlalchemy"
Requires-Dist: sqlalchemy-bigquery (>=1.6.1,<2.0.0) ; python_version >= "3.9" and python_version < "3.12"
Requires-Dist: tqdm (>=4.65.0,<5.0.0)
Requires-Dist: wrapt (>=1.15.0,<2.0.0)
